infra/__init__.py
infra/__main__.py
ksubmit/__init__.py
ksubmit/cli/__init__.py
ksubmit/cli/config.py
ksubmit/cli/delete.py
ksubmit/cli/describe.py
ksubmit/cli/lint.py
ksubmit/cli/list.py
ksubmit/cli/logs.py
ksubmit/cli/main.py
ksubmit/cli/shorthand.py
ksubmit/cli/status.py
ksubmit/cli/submit.py
ksubmit/config/__init__.py
ksubmit/config/constants.py
ksubmit/config/user_config.py
ksubmit/kubernetes/__init__.py
ksubmit/kubernetes/client.py
ksubmit/kubernetes/job.py
ksubmit/linting/__init__.py
ksubmit/linting/lint.py
ksubmit/parsers/__init__.py
ksubmit/parsers/dsl.py
ksubmit/utils/__init__.py
ksubmit/utils/database.py
ksubmit/utils/formatting.py
ksubmit/utils/identifiers.py
ksubmit/utils/storage.py
ksubmit-0.1.10.dist-info/licenses/LICENSE.md
tests/__init__.py
tests/conftest.py
tests/cli/__init__.py
tests/config/__init__.py
tests/kubernetes/__init__.py
tests/kubernetes/test_entrypoint.py
tests/kubernetes/test_job_name.py
tests/linting/__init__.py
tests/linting/test_lint.py
tests/parsers/__init__.py
tests/utils/__init__.py
ksubmit-0.1.10.dist-info/METADATA
ksubmit-0.1.10.dist-info/WHEEL
ksubmit-0.1.10.dist-info/entry_points.txt
ksubmit-0.1.10.dist-info/top_level.txt
ksubmit-0.1.10.dist-info/RECORD
