Metadata-Version: 2.4
Name: ksubmit
Version: 0.1.10
Summary: KSUBMIT (pronounced “submit” — silent “k”) is a Python CLI tool that makes it easy to submit batch jobs to Kubernetes. Using a simple syntax inspired by Univa Grid Engine, it helps you run HPC-style workloads on Kubernetes without needing to write complex YAML files
Home-page: https://github.com/obistack/ksubmit
Author: John Kitonyo
Author-email: johnkitonyo@outlook.com
License: MIT
Project-URL: Documentation, https://github.com/obistack/ksubmit
Project-URL: Source, https://github.com/obistack/ksubmit
Project-URL: Bug Tracker, https://github.com/obistack/ksubmit/issues
Keywords: kubernetes,batch,jobs,cli,hpc,grid-engine,uge,job-scheduler
Classifier: Development Status :: 4 - Beta
Classifier: Intended Audience :: Developers
Classifier: Intended Audience :: Science/Research
Classifier: Intended Audience :: System Administrators
Classifier: License :: OSI Approved :: MIT License
Classifier: Programming Language :: Python :: 3
Classifier: Programming Language :: Python :: 3.8
Classifier: Programming Language :: Python :: 3.9
Classifier: Programming Language :: Python :: 3.10
Classifier: Programming Language :: Python :: 3.11
Classifier: Topic :: System :: Clustering
Classifier: Topic :: System :: Distributed Computing
Classifier: Topic :: Scientific/Engineering
Classifier: Operating System :: OS Independent
Requires-Python: >=3.8
License-File: LICENSE.md
Requires-Dist: typer
Requires-Dist: pyyaml
Requires-Dist: kubernetes
Requires-Dist: python-dotenv
Requires-Dist: rich
Requires-Dist: duckdb
Provides-Extra: dev
Requires-Dist: pytest; extra == "dev"
Requires-Dist: pytest-cov; extra == "dev"
Dynamic: author
Dynamic: author-email
Dynamic: classifier
Dynamic: description
Dynamic: description-content-type
Dynamic: home-page
Dynamic: keywords
Dynamic: license
Dynamic: license-file
Dynamic: project-url
Dynamic: provides-extra
Dynamic: requires-dist
Dynamic: requires-python
Dynamic: summary
